temp/generated_rtl.v
module four_bit_adder (
    input [3:0] A,
    input [3:0] B,
    input Cin,
    output [3:0] S,
    output Cout
);

    wire [3:0] sum;
    wire [3:0] carry;

    assign sum = A + B + Cin;
    assign Cout = carry[3];

    assign carry[0] = (A[0] & B[0]) | (A[0] & Cin) | (B[0] & Cin);
    assign carry[1] = (A[1] & B[1]) | (A[1] & carry[0]) | (B[1] & carry[0]);
    assign carry[2] = (A[2] & B[2]) | (A[2] & carry[1]) | (B[2] & carry[1]);
    assign carry[3] = (A[3] & B[3]) | (A[3] & carry[2]) | (B[3] & carry[2]);

    assign S = sum;

endmodule

temp/tb.v
module tb;

reg [3:0] A;
reg [3:0] B;
reg Cin;
wire [3:0] S;
wire Cout;

four_bit_adder uut (
.A(A),
.B(B),
.Cin(Cin),
.S(S),
.Cout(Cout)
);

integer i;
integer errors = 0;


initial begin
    $dumpfile("temp/wave.vcd");
    $dumpvars(0, tb);

    repeat (20) begin
        A = $random;
        B = $random;
        Cin = $random;

        #5;

        // 🔥 BASIC SANITY CHECK
        if (S === 1'bx) errors = errors + 1;
        if (Cout === 1'bx) errors = errors + 1;

    end

    if (errors == 0)
        $display("FINAL_RESULT: PASS");
    else
        $display("FINAL_RESULT: FAIL");

    $finish;
end

endmodule

temp/wave.vcd
$date
	Wed Apr 08 13:01:33 2026
$end
$version
	Icarus Verilog
$end
$timescale
	1s
$end
$scope module tb $end
$var wire 4 ! S [3:0] $end
$var wire 1 " Cout $end
$var reg 4 # A [3:0] $end
$var reg 4 $ B [3:0] $end
$var reg 1 % Cin $end
$var integer 32 & errors [31:0] $end
$scope module uut $end
$var wire 4 ' A [3:0] $end
$var wire 4 ( B [3:0] $end
$var wire 1 % Cin $end
$var wire 4 ) S [3:0] $end
$var wire 4 * sum [3:0] $end
$var wire 4 + carry [3:0] $end
$var wire 1 " Cout $end
$upscope $end
$upscope $end
$enddefinitions $end
$comment Show the parameter values. $end
$dumpall
$end
#0
$dumpvars
b1 +
b110 *
b110 )
b1 (
b100 '
b0 &
1%
b1 $
b100 #
0"
b110 !
$end
#5
1"
b1111 +
b1101 $
b1101 (
b1 !
b1 )
b1 *
b11 #
b11 '
#10
0"
b111 +
b10 $
b10 (
b1000 !
b1000 )
b1000 *
b101 #
b101 '
#15
1"
b1111 +
b110 $
b110 (
b100 !
b100 )
b100 *
b1101 #
b1101 '
#20
b1101 +
b1010 !
b1010 )
b1010 *
b1100 $
b1100 (
#25
0"
b100 +
0%
b101 $
b101 (
b1011 !
b1011 )
b1011 *
b110 #
b110 '
#30
b111 +
b111 $
b111 (
b1100 !
b1100 )
b1100 *
b101 #
b101 '
#35
1"
b1110 +
b10 $
b10 (
b1 !
b1 )
b1 *
b1111 #
b1111 '
#40
0"
b0 +
b101 $
b101 (
b1101 !
b1101 )
b1101 *
b1000 #
b1000 '
#45
1"
b1101 +
1%
b1101 $
b1101 (
b1011 !
b1011 )
b1011 *
b1101 #
b1101 '
#50
0"
b10 +
0%
b1010 $
b1010 (
b1101 !
b1101 )
b1101 *
b11 #
b11 '
#55
b0 +
1%
b1011 !
b1011 )
b1011 *
b0 #
b0 '
#60
b111 +
b11 $
b11 (
b1010 !
b1010 )
b1010 *
b110 #
b110 '
#65
0"
b11 +
b1011 $
b1011 (
b1111 !
b1111 )
b1111 *
b11 #
b11 '
#70
1"
b1110 +
b1110 $
b1110 (
b1 !
b1 )
b1 *
b10 #
b10 '
#75
b1111 +
0%
b11 $
b11 (
b10 !
b10 )
b10 *
b1111 #
b1111 '
#80
b1000 +
b1100 $
b1100 (
b110 !
b110 )
b110 *
b1010 #
b1010 '
#85
0"
b0 +
b1011 !
b1011 )
b1011 *
b1 $
b1 (
#90
1"
b1001 +
1%
b1001 $
b1001 (
b10 !
b10 )
b10 *
b1000 #
b1000 '
#95
0"
b110 +
0%
b110 $
b110 (
b1100 !
b1100 )
b1100 *
b110 #
b110 '
